ARC/__init__.py
ARC/__main__.py
ARC/classifier.py
ARC/mhc_G_domain.py
ARC/data/MHC_HMMs.zip
ARC/data/MRO_Gdomain.csv
ARC/data/blastdb.zip
ARC/data/chain-sequence.tsv
ARC/data/HMMs/ALL.hmm
ARC/data/HMMs/ALL.hmm.h3f
ARC/data/HMMs/ALL.hmm.h3i
ARC/data/HMMs/ALL.hmm.h3m
ARC/data/HMMs/ALL.hmm.h3p
ARC/data/HMMs/ALL_AND_C.hmm
ARC/data/HMMs/ALL_AND_C.hmm.h3f
ARC/data/HMMs/ALL_AND_C.hmm.h3i
ARC/data/HMMs/ALL_AND_C.hmm.h3m
ARC/data/HMMs/ALL_AND_C.hmm.h3p
ARC/data/IgNAR/IgNAR.phr
ARC/data/IgNAR/IgNAR.pin
ARC/data/IgNAR/IgNAR.psq
ARC/data/IgNAR/IgNAR_all_sources.fasta
ARC/data/IgNAR_source_data/IgNAR_all_sources.muscle
ARC/data/IgNAR_source_data/IgNAR_from_IEDB.fasta
ARC/data/IgNAR_source_data/IgNAR_from_NCBI.fasta
ARC/data/IgNAR_source_data/IgNAR_from_uniprot.fasta
ARC/data/IgNAR_source_data/IgNAR_from_uniprot_results.txt
ARC/data/IgNAR_source_data/IgNAR_from_uniprot_results.xml
ARC/data/IgNAR_source_data/IgNARs_PDB.csv
ARC/data/IgNAR_source_data/all_mhcBcrTcr_IEDB.fasta
ARC/data/IgNAR_source_data/all_mhc_bcrtcr_BLASTP_results.txt
ARC/data/MHC_HMMs/DTU_MHC_I_complete.hmm
ARC/data/MHC_HMMs/DTU_MHC_I_complete.hmm.h3f
ARC/data/MHC_HMMs/DTU_MHC_I_complete.hmm.h3i
ARC/data/MHC_HMMs/DTU_MHC_I_complete.hmm.h3m
ARC/data/MHC_HMMs/DTU_MHC_I_complete.hmm.h3p
ARC/data/MHC_HMMs/Pfam_MHC_I.hmm
ARC/data/MHC_HMMs/Pfam_MHC_I.hmm.h3f
ARC/data/MHC_HMMs/Pfam_MHC_I.hmm.h3i
ARC/data/MHC_HMMs/Pfam_MHC_I.hmm.h3m
ARC/data/MHC_HMMs/Pfam_MHC_I.hmm.h3p
ARC/data/MHC_HMMs/Pfam_MHC_II_alpha.hmm
ARC/data/MHC_HMMs/Pfam_MHC_II_alpha.hmm.h3f
ARC/data/MHC_HMMs/Pfam_MHC_II_alpha.hmm.h3i
ARC/data/MHC_HMMs/Pfam_MHC_II_alpha.hmm.h3m
ARC/data/MHC_HMMs/Pfam_MHC_II_alpha.hmm.h3p
ARC/data/MHC_HMMs/Pfam_MHC_II_beta.hmm
ARC/data/MHC_HMMs/Pfam_MHC_II_beta.hmm.h3f
ARC/data/MHC_HMMs/Pfam_MHC_II_beta.hmm.h3i
ARC/data/MHC_HMMs/Pfam_MHC_II_beta.hmm.h3m
ARC/data/MHC_HMMs/Pfam_MHC_II_beta.hmm.h3p
ARC/data/blastdb/G_ALPHA.fasta
ARC/data/blastdb/G_ALPHA.fasta.phr
ARC/data/blastdb/G_ALPHA.fasta.pin
ARC/data/blastdb/G_ALPHA.fasta.psq
bio_arc-0.1.1.dist-info/LICENSE
bio_arc-0.1.1.dist-info/METADATA
bio_arc-0.1.1.dist-info/WHEEL
bio_arc-0.1.1.dist-info/top_level.txt
bio_arc-0.1.1.dist-info/RECORD
