Metadata-Version: 2.1
Name: bio-arc
Version: 0.1.1
Summary: Antigen Receptor Classifier
Home-page: https://github.com/iedb/arc
Author: Austin Crinklaw
Author-email: acrinklaw@lji.org
License: UNKNOWN
Platform: UNKNOWN
Classifier: Programming Language :: Python :: 3
Classifier: Operating System :: Unix
Requires-Dist: biopython
Requires-Dist: numpy
Requires-Dist: pandas
